CHANGELOG.md
LICENSE
MANIFEST.in
README.md
setup.py
bench_fio/__init__.py
bench_fio/__main__.py
bench_fio/benchlib/__init__.py
bench_fio/benchlib/argparsing.py
bench_fio/benchlib/checks.py
bench_fio/benchlib/defaultsettings.py
bench_fio/benchlib/display.py
bench_fio/benchlib/generatefio.py
bench_fio/benchlib/network.py
bench_fio/benchlib/parseini.py
bench_fio/benchlib/runfio.py
bench_fio/benchlib/supporting.py
bench_fio/scripts/bench-fio.sh
bench_fio/scripts/generate_call_graph.sh
bench_fio/templates/precondition.fio
bin/bench-fio
bin/fio-plot
docs/bench_fio_call_graph.png
docs/fio_plot_call_graph.png
docs/generate_call_graph.sh
fio_plot/__init__.py
fio_plot/__main__.py
fio_plot.egg-info/PKG-INFO
fio_plot.egg-info/SOURCES.txt
fio_plot.egg-info/dependency_links.txt
fio_plot.egg-info/entry_points.txt
fio_plot.egg-info/requires.txt
fio_plot.egg-info/top_level.txt
fio_plot/fiolib/__init__.py
fio_plot/fiolib/argparsing.py
fio_plot/fiolib/bar2d.py
fio_plot/fiolib/bar3d.py
fio_plot/fiolib/barhistogram.py
fio_plot/fiolib/dataimport.py
fio_plot/fiolib/dataimport_support.py
fio_plot/fiolib/defaultsettings.py
fio_plot/fiolib/flightchecks.py
fio_plot/fiolib/getdata.py
fio_plot/fiolib/graph2d.py
fio_plot/fiolib/graph2dsupporting.py
fio_plot/fiolib/iniparsing.py
fio_plot/fiolib/iniparsing_support.py
fio_plot/fiolib/jsonimport.py
fio_plot/fiolib/jsonparsing.py
fio_plot/fiolib/jsonparsing_support.py
fio_plot/fiolib/shared_chart.py
fio_plot/fiolib/supporting.py
fio_plot/fiolib/table_support.py
fio_plot/fiolib/tables.py
tests/bench_fio_test.py
tests/test_3d.py