Metadata-Version: 2.1
Name: fio-plot
Version: 1.1.14
Summary: Create charts from FIO storage benchmark tool output
Home-page: https://github.com/louwrentius/fio-plot/
Author: louwrentius
License-File: LICENSE
Requires-Dist: numpy
Requires-Dist: matplotlib
Requires-Dist: Pillow
Requires-Dist: pyan3
Requires-Dist: pyparsing
Requires-Dist: rich
